gbwog/panel/.git-easy-crypt-key
gbwog/panel/CurrencyRoulette.py
gbwog/panel/Game.py
gbwog/panel/GuessGame.py
gbwog/panel/Live.py
gbwog/panel/MainGame.py
gbwog/panel/MemoryGame.py
gbwog/panel/Score.py
gbwog/panel/Utils.py
gbwog/panel/__init__.py
gbwog/panel/curr.key.sec
gbwog/website/MainScores.py
gbwog/website/Utils.py
gbwog/website/__init__.py
gbwog.website-1.0.5.dist-info/LICENSE
gbwog.website-1.0.5.dist-info/METADATA
gbwog.website-1.0.5.dist-info/WHEEL
gbwog.website-1.0.5.dist-info/top_level.txt
gbwog.website-1.0.5.dist-info/RECORD
